slippers.py
slippers_proxy-0.3.0.dist-info/LICENSE
slippers_proxy-0.3.0.dist-info/METADATA
slippers_proxy-0.3.0.dist-info/WHEEL
slippers_proxy-0.3.0.dist-info/RECORD
