Metadata-Version: 2.1
Name: slippers-proxy
Version: 0.3.0
Summary: 
License: MIT
Author: Ryan Siemens
Author-email: ryanjsiemens@gmail.com
Requires-Python: >=3.11,<4.0
Classifier: License :: OSI Approved :: MIT License
Classifier: Programming Language :: Python :: 3
Classifier: Programming Language :: Python :: 3.11
Classifier: Programming Language :: Python :: 3.12
